odoo/addons/purchase_report_date_format/README.rst
odoo/addons/purchase_report_date_format/__init__.py
odoo/addons/purchase_report_date_format/__manifest__.py
odoo/addons/purchase_report_date_format/i18n/it.po
odoo/addons/purchase_report_date_format/i18n/pt_BR.po
odoo/addons/purchase_report_date_format/i18n/purchase_report_date_format.pot
odoo/addons/purchase_report_date_format/readme/DESCRIPTION.rst
odoo/addons/purchase_report_date_format/reports/purchase_order_templates.xml
odoo/addons/purchase_report_date_format/reports/purchase_quotation_templates.xml
odoo/addons/purchase_report_date_format/static/description/icon.png
odoo/addons/purchase_report_date_format/static/description/index.html
odoo14_addon_purchase_report_date_format-14.0.1.0.1.dev1.dist-info/METADATA
odoo14_addon_purchase_report_date_format-14.0.1.0.1.dev1.dist-info/WHEEL
odoo14_addon_purchase_report_date_format-14.0.1.0.1.dev1.dist-info/top_level.txt
odoo14_addon_purchase_report_date_format-14.0.1.0.1.dev1.dist-info/RECORD
